LICENSE
MANIFEST.in
README.rst
requirements.txt
setup.py
pylama_gjslint/__init__.py
pylama_gjslint/main.py
pylama_gjslint.egg-info/PKG-INFO
pylama_gjslint.egg-info/SOURCES.txt
pylama_gjslint.egg-info/dependency_links.txt
pylama_gjslint.egg-info/entry_points.txt
pylama_gjslint.egg-info/pbr.json
pylama_gjslint.egg-info/requires.txt
pylama_gjslint.egg-info/top_level.txt
pylama_gjslint/closure_linter/__init__.py
pylama_gjslint/closure_linter/aliaspass.py
pylama_gjslint/closure_linter/aliaspass_test.py
pylama_gjslint/closure_linter/checker.py
pylama_gjslint/closure_linter/checkerbase.py
pylama_gjslint/closure_linter/closurizednamespacesinfo.py
pylama_gjslint/closure_linter/closurizednamespacesinfo_test.py
pylama_gjslint/closure_linter/ecmalintrules.py
pylama_gjslint/closure_linter/ecmametadatapass.py
pylama_gjslint/closure_linter/error_check.py
pylama_gjslint/closure_linter/error_fixer.py
pylama_gjslint/closure_linter/error_fixer_test.py
pylama_gjslint/closure_linter/errorrecord.py
pylama_gjslint/closure_linter/errorrules.py
pylama_gjslint/closure_linter/errorrules_test.py
pylama_gjslint/closure_linter/errors.py
pylama_gjslint/closure_linter/fixjsstyle.py
pylama_gjslint/closure_linter/fixjsstyle_test.py
pylama_gjslint/closure_linter/full_test.py
pylama_gjslint/closure_linter/gjslint.py
pylama_gjslint/closure_linter/indentation.py
pylama_gjslint/closure_linter/javascriptlintrules.py
pylama_gjslint/closure_linter/javascriptstatetracker.py
pylama_gjslint/closure_linter/javascriptstatetracker_test.py
pylama_gjslint/closure_linter/javascripttokenizer.py
pylama_gjslint/closure_linter/javascripttokens.py
pylama_gjslint/closure_linter/not_strict_test.py
pylama_gjslint/closure_linter/requireprovidesorter.py
pylama_gjslint/closure_linter/requireprovidesorter_test.py
pylama_gjslint/closure_linter/runner.py
pylama_gjslint/closure_linter/runner_test.py
pylama_gjslint/closure_linter/scopeutil.py
pylama_gjslint/closure_linter/scopeutil_test.py
pylama_gjslint/closure_linter/statetracker.py
pylama_gjslint/closure_linter/statetracker_test.py
pylama_gjslint/closure_linter/testutil.py
pylama_gjslint/closure_linter/tokenutil.py
pylama_gjslint/closure_linter/tokenutil_test.py
pylama_gjslint/closure_linter/common/__init__.py
