Metadata-Version: 1.1
Name: pylama-gjslint
Version: 0.0.8
Summary: Gjslint integration to pylama library.
